py4me/__init__.py
py4me/enums.py
py4me/exceptions.py
py4me/filters.py
py4me/py4me.py
py4me/serialization.py
py4me/_api/__init__.py
py4me/_api/py4me_api.py
py4me/account/__init__.py
py4me/account/models.py
py4me/auth/__init__.py
py4me/auth/auth.py
py4me/organizations/__init__.py
py4me/organizations/models.py
py4me/other_models/__init__.py
py4me/other_models/address.py
py4me/other_models/custom_field.py
py4me/people/__init__.py
py4me/people/models.py
py4me/people/people_api.py
tests/__init__.py
tests/test_enums.py
tests/test_filters.py
tests/tests_py4me.py
tests/tests_py4me_api.py
tests/tests_serialization.py
py4me-0.0.2.dist-info/METADATA
py4me-0.0.2.dist-info/WHEEL
py4me-0.0.2.dist-info/top_level.txt
py4me-0.0.2.dist-info/RECORD
